stucancommon/__init__.py
stucancommon/driver.py
stucancommon/node.py
stucancommon-0.9.2.dist-info/LICENSE
stucancommon-0.9.2.dist-info/METADATA
stucancommon-0.9.2.dist-info/WHEEL
stucancommon-0.9.2.dist-info/top_level.txt
stucancommon-0.9.2.dist-info/RECORD
