Metadata-Version: 2.1
Name: stucancommon
Version: 0.9.2
Summary: Package that let access a CAN bus
Home-page: https://github.com/studer-innotec/stucancommon
Author: Studer Innotec SA
Author-email: develop@studer-innotec.com
Maintainer-email: develop@studer-innotec.com
License: MIT
Project-URL: Documentation, https://stucancommon.readthedocs.io/en/latest/index.html
Project-URL: Issues tracker, https://github.com/studer-innotec/stucancommon/issues
Project-URL: Source Code, https://github.com/studer-innotec/stucancommon
Platform: UNKNOWN
Classifier: Programming Language :: Python :: 3
Classifier: License :: OSI Approved :: MIT License
Classifier: Operating System :: OS Independent
Classifier: Development Status :: 4 - Beta
Classifier: Topic :: Communications
Classifier: Topic :: Software Development :: Libraries
Classifier: Topic :: Software Development :: Libraries :: Python Modules
Requires-Python: >=3.6.8
Requires-Dist: python-can (>=3.3.2)
